Metadata-Version: 2.1
Name: nonebot-plugin-random-draw
Version: 0.1.0
Summary: 通过添加各种想要抽取的内容，最后进行随机抽取。
Home-page: https://github.com/Ikaros-521/nonebot_plugin_random_draw
License: MIT
Author: Ikaros
Author-email: 327209194@qq.com
Requires-Python: >=3.8,<4.0
Classifier: License :: OSI Approved :: MIT License
Classifier: Programming Language :: Python :: 3
Classifier: Programming Language :: Python :: 3.8
Classifier: Programming Language :: Python :: 3.9
Classifier: Programming Language :: Python :: 3.10
Classifier: Programming Language :: Python :: 3.11
Requires-Dist: nonebot-adapter-onebot (>=2.1.3,<3.0.0)
Requires-Dist: nonebot2 (>=2.0.0b5,<3.0.0)
Project-URL: Documentation, https://github.com/Ikaros-521/nonebot_plugin_random_draw/blob/master/README.md
Project-URL: Repository, https://github.com/Ikaros-521/nonebot_plugin_random_draw
